dishpy/__init__.py
dishpy/amalgamator.py
dishpy/download_vexcom.sh
dishpy/main.py
dishpy/utils.py
dishpy/vexcom.py
dishpy/resources/pkg_template.py
dishpy/resources/template.py
dishpy/resources/vex.md
dishpy/resources/vex.py
dishpy/resources/templates/clawbot.py
dishpy/resources/templates/clawbot_controller_tank.py
dishpy/resources/templates/competition_template.py
dishpy/resources/templates/drive_to_location_gps.py
dishpy/resources/templates/drivetrain_sensing.py
dishpy/resources/templates/empty.py
dishpy/resources/templates/limit_bumper_sensing.py
dishpy/resources/templates/right_arcade_control.py
dishpy/resources/templates/split_arcade_control.py
dishpy/resources/templates/using_threads.py
dishpy-1.2.1.dist-info/METADATA
dishpy-1.2.1.dist-info/WHEEL
dishpy-1.2.1.dist-info/entry_points.txt
dishpy-1.2.1.dist-info/licenses/LICENSE
dishpy-1.2.1.dist-info/RECORD
