Metadata-Version: 2.4
Name: dishpy
Version: 1.2.1
Summary: A Python development tool for VEX Competition robotics that combines multi-file Python projects into single scripts and uploads them to VEX V5 brains
Project-URL: Homepage, https://github.com/aadishv/dishpy
Project-URL: Repository, https://github.com/aadishv/dishpy
Project-URL: Issues, https://github.com/aadishv/dishpy/issues
Project-URL: Documentation, https://github.com/aadishv/dishpy#readme
Author-email: Aadish V <aadish@ohs.stanford.edu>
Maintainer-email: Aadish V <aadish@ohs.stanford.edu>
License: MIT License
License-File: LICENSE
Keywords: competition,development-tool,python,robotics,v5,vex
Classifier: Development Status :: 4 - Beta
Classifier: Environment :: Console
Classifier: Intended Audience :: Developers
Classifier: Intended Audience :: Education
Classifier: License :: OSI Approved :: MIT License
Classifier: Operating System :: OS Independent
Classifier: Programming Language :: Python :: 3
Classifier: Programming Language :: Python :: 3.12
Classifier: Programming Language :: Python :: 3.13
Classifier: Topic :: Education
Classifier: Topic :: Software Development :: Build Tools
Classifier: Topic :: Software Development :: Code Generators
Requires-Python: >=3.12
Requires-Dist: platformdirs>=4.0.0
Requires-Dist: requests>=2.32.3
Requires-Dist: rich>=14.0.0
Requires-Dist: textcase>=0.4.3
Requires-Dist: tomli-w>=1.2.0
Requires-Dist: tomli>=1.2.0; python_version < '3.11'
Requires-Dist: validators>=0.35.0
Provides-Extra: dev
Requires-Dist: black>=23.0.0; extra == 'dev'
Requires-Dist: pytest>=7.0.0; extra == 'dev'
Requires-Dist: ruff>=0.1.0; extra == 'dev'
